synpla_weight/__init__.py
synpla_weight/static/js/app-weight.js
synpla_weight/templates/weight/macros/hiddenfield.html
synpla_weight-0.1.1.dist-info/RECORD
synpla_weight-0.1.1.dist-info/DESCRIPTION.rst
synpla_weight-0.1.1.dist-info/top_level.txt
synpla_weight-0.1.1.dist-info/METADATA
synpla_weight-0.1.1.dist-info/WHEEL
synpla_weight-0.1.1.dist-info/metadata.json
